bio2bel_mesh/__init__.py
bio2bel_mesh/__main__.py
bio2bel_mesh/cli.py
bio2bel_mesh/constants.py
bio2bel_mesh/convert.py
bio2bel_mesh/manager.py
bio2bel_mesh/models.py
bio2bel_mesh/utils.py
bio2bel_mesh/parsers/__init__.py
bio2bel_mesh/parsers/descriptors.py
bio2bel_mesh/parsers/supplement.py
bio2bel_mesh/parsers/utils.py
bio2bel_mesh-0.2.0.dist-info/LICENSE
bio2bel_mesh-0.2.0.dist-info/METADATA
bio2bel_mesh-0.2.0.dist-info/WHEEL
bio2bel_mesh-0.2.0.dist-info/entry_points.txt
bio2bel_mesh-0.2.0.dist-info/top_level.txt
bio2bel_mesh-0.2.0.dist-info/RECORD
