Metadata-Version: 2.1
Name: bio2bel-mesh
Version: 0.2.0
Summary: A package for converting MeSH to BEL
Home-page: https://github.com/bio2bel/mesh
Author: Charles Tapley Hoyt
Author-email: charles.hoyt@scai.fraunhofer.de
Maintainer: Charles Tapley Hoyt
Maintainer-email: charles.hoyt@scai.fraunhofer.de
License: MIT License
Keywords: Biological Expression Language,BEL,Systems Biology,Networks Biology,MeSH
Platform: UNKNOWN
Classifier: Development Status :: 4 - Beta
Classifier: Environment :: Console
Classifier: Intended Audience :: Developers
Classifier: Intended Audience :: Science/Research
Classifier: License :: OSI Approved :: MIT License
Classifier: Operating System :: OS Independent
Classifier: Programming Language :: Python
Classifier: Programming Language :: Python :: 3.6
Classifier: Programming Language :: Python :: 3.7
Classifier: Topic :: Scientific/Engineering :: Bio-Informatics
Requires-Dist: pybel (<0.13.0,>=0.12.0)
Requires-Dist: bio2bel (<0.3.0,>=0.2.0)
Requires-Dist: sqlalchemy
Requires-Dist: click
Requires-Dist: requests
Requires-Dist: rdflib
Requires-Dist: networkx
Requires-Dist: tqdm
Provides-Extra: owl
Requires-Dist: owlready; extra == 'owl'
Provides-Extra: web
Requires-Dist: flask; extra == 'web'
Requires-Dist: flask-admin; extra == 'web'
